odoo/addons/partner_certificate_of_conduct/README.rst
odoo/addons/partner_certificate_of_conduct/__init__.py
odoo/addons/partner_certificate_of_conduct/__manifest__.py
odoo/addons/partner_certificate_of_conduct/data/res_partner_id_category_data.xml
odoo/addons/partner_certificate_of_conduct/i18n/partner_certificate_of_conduct.pot
odoo/addons/partner_certificate_of_conduct/models/__init__.py
odoo/addons/partner_certificate_of_conduct/models/res_partner.py
odoo/addons/partner_certificate_of_conduct/readme/CONTRIBUTORS.rst
odoo/addons/partner_certificate_of_conduct/readme/DESCRIPTION.rst
odoo/addons/partner_certificate_of_conduct/readme/USAGE.rst
odoo/addons/partner_certificate_of_conduct/static/description/icon.png
odoo/addons/partner_certificate_of_conduct/static/description/index.html
odoo/addons/partner_certificate_of_conduct/tests/__init__.py
odoo/addons/partner_certificate_of_conduct/tests/test_partner_certificate_of_conduct.py
odoo/addons/partner_certificate_of_conduct/views/res_partner_view.xml
odoo11_addon_partner_certificate_of_conduct-11.0.1.0.0.99.dev6.dist-info/METADATA
odoo11_addon_partner_certificate_of_conduct-11.0.1.0.0.99.dev6.dist-info/WHEEL
odoo11_addon_partner_certificate_of_conduct-11.0.1.0.0.99.dev6.dist-info/top_level.txt
odoo11_addon_partner_certificate_of_conduct-11.0.1.0.0.99.dev6.dist-info/RECORD
